himalayas/__init__.py
himalayas-0.0.1.dist-info/licenses/LICENSE
himalayas-0.0.1.dist-info/METADATA
himalayas-0.0.1.dist-info/WHEEL
himalayas-0.0.1.dist-info/top_level.txt
himalayas-0.0.1.dist-info/RECORD
