Metadata-Version: 2.4
Name: himalayas
Version: 0.0.1
Summary: Hierarchical Matrix Layout and Annotation Software
Author: Ira Horecka
License: BSD 3-Clause License
Project-URL: Homepage, https://github.com/himalayas-base/himalayas
Project-URL: Repository, https://github.com/himalayas-base/himalayas
Classifier: Development Status :: 2 - Pre-Alpha
Classifier: Intended Audience :: Science/Research
Classifier: License :: OSI Approved :: BSD License
Classifier: Programming Language :: Python :: 3
Classifier: Operating System :: OS Independent
Requires-Python: >=3.8
License-File: LICENSE
Dynamic: license-file
